[
  {
    "type": "post",
    "url": "/addApply",
    "title": "申请点赞币",
    "name": "addApply",
    "group": "User",
    "parameter": {
      "fields": {
        "Parameter": [
          {
            "group": "Parameter",
            "type": "String",
            "optional": false,
            "field": "applyContent",
            "description": "<p>申请点赞币具体内容，包括申请给哪些人，张数以及描述，要求为json数据.</p>"
          },
          {
            "group": "Parameter",
            "type": "Number",
            "optional": false,
            "field": "applyType",
            "description": "<p>点赞币申请类型的id.</p>"
          }
        ]
      }
    },
    "success": {
      "fields": {
        "Success 200": [
          {
            "group": "Success 200",
            "type": "Number",
            "optional": false,
            "field": "code",
            "description": "<p>状态码 0正常</p>"
          },
          {
            "group": "Success 200",
            "type": "String",
            "optional": false,
            "field": "msg",
            "description": "<p>响应信息.</p>"
          }
        ]
      },
      "examples": [
        {
          "title": "Success-Response:",
          "content": "HTTP/1.1 200 OK\n{\n  \"code\": \"0\",\n  \"msg\": \"success\",\n}",
          "type": "json"
        }
      ]
    },
    "error": {
      "fields": {
        "Error 4xx": [
          {
            "group": "Error 4xx",
            "optional": false,
            "field": "UserNotFound",
            "description": "<p>The id of the User was not found.</p>"
          }
        ]
      },
      "examples": [
        {
          "title": "Error-Response:",
          "content": "HTTP/1.1 200\n{\n  \"code\": \"1\",\n   \"msg\": '响应的报错信息'\n}",
          "type": "json"
        }
      ]
    },
    "version": "0.0.0",
    "filename": "app/Http/Controllers/User/PersonalCenter.php",
    "groupTitle": "User"
  },
  {
    "type": "post",
    "url": "/addTalk",
    "title": "添加匿名聊天",
    "name": "addTalk",
    "group": "User",
    "parameter": {
      "fields": {
        "Parameter": [
          {
            "group": "Parameter",
            "type": "String",
            "optional": false,
            "field": "content",
            "description": "<p>内容</p>"
          }
        ]
      }
    },
    "success": {
      "fields": {
        "Success 200": [
          {
            "group": "Success 200",
            "type": "Number",
            "optional": false,
            "field": "code",
            "description": "<p>状态码 0正常</p>"
          },
          {
            "group": "Success 200",
            "type": "String",
            "optional": false,
            "field": "msg",
            "description": "<p>响应信息.</p>"
          }
        ]
      },
      "examples": [
        {
          "title": "Success-Response:",
          "content": "HTTP/1.1 200 OK\n{\n  \"code\": \"0\",\n  \"msg\": \"success\",\n}",
          "type": "json"
        }
      ]
    },
    "error": {
      "fields": {
        "Error 4xx": [
          {
            "group": "Error 4xx",
            "optional": false,
            "field": "UserNotFound",
            "description": "<p>The id of the User was not found.</p>"
          }
        ]
      },
      "examples": [
        {
          "title": "Error-Response:",
          "content": "HTTP/1.1 200\n{\n  \"code\": \"1\",\n   \"msg\": '响应的报错信息'\n}",
          "type": "json"
        }
      ]
    },
    "version": "0.0.0",
    "filename": "app/Http/Controllers/User/PersonalCenter.php",
    "groupTitle": "User"
  },
  {
    "type": "get",
    "url": "/getApplyType",
    "title": "返回类型列表",
    "name": "getApplyType",
    "group": "User",
    "success": {
      "fields": {
        "Success 200": [
          {
            "group": "Success 200",
            "type": "Number",
            "optional": false,
            "field": "id",
            "description": "<p>类型id</p>"
          },
          {
            "group": "Success 200",
            "type": "String",
            "optional": false,
            "field": "type_name",
            "description": "<p>类型名称.</p>"
          }
        ]
      },
      "examples": [
        {
          "title": "Success-Response:",
          "content": "HTTP/1.1 200 OK\n{\n  \"code\": \"0\",\n  \"msg\": \"success\",\n  \"data\":{\n             id:,\n             type_name:\n         }\n}",
          "type": "json"
        }
      ]
    },
    "error": {
      "fields": {
        "Error 4xx": [
          {
            "group": "Error 4xx",
            "optional": false,
            "field": "UserNotFound",
            "description": "<p>The id of the User was not found.</p>"
          }
        ]
      },
      "examples": [
        {
          "title": "Error-Response:",
          "content": "HTTP/1.1 200\n{\n  \"code\": \"1\",\n   \"msg\": '响应的报错信息'\n}\n\n HTTP/1.1 200\n{\n  \"code\": \"2\",\n   \"msg\": '无数据'\n}",
          "type": "json"
        }
      ]
    },
    "version": "0.0.0",
    "filename": "app/Http/Controllers/User/PersonalCenter.php",
    "groupTitle": "User"
  },
  {
    "type": "get",
    "url": "/getBuyOrder",
    "title": "查询需要处理的订单列表",
    "name": "getBuyOrder",
    "group": "User",
    "success": {
      "fields": {
        "Success 200": [
          {
            "group": "Success 200",
            "type": "Number",
            "optional": false,
            "field": "id",
            "description": "<p>对应订单id</p>"
          },
          {
            "group": "Success 200",
            "type": "String",
            "optional": false,
            "field": "user_id",
            "description": "<p>对应用户id</p>"
          },
          {
            "group": "Success 200",
            "type": "String",
            "optional": false,
            "field": "content",
            "description": "<p>购买内容.</p>"
          },
          {
            "group": "Success 200",
            "type": "String",
            "optional": false,
            "field": "name",
            "description": "<p>用户名称.</p>"
          },
          {
            "group": "Success 200",
            "type": "Number",
            "optional": false,
            "field": "qq_account",
            "description": "<p>用户qq号</p>"
          }
        ]
      },
      "examples": [
        {
          "title": "Success-Response:",
          "content": "HTTP/1.1 200 OK\n{\n  \"code\": \"0\",\n  \"msg\": \"success\",\n  \"data\":{\n             id:,\n             user_id:,\n             content:,\n             name:,\n             qq_account:\n         }\n}",
          "type": "json"
        }
      ]
    },
    "error": {
      "fields": {
        "Error 4xx": [
          {
            "group": "Error 4xx",
            "optional": false,
            "field": "UserNotFound",
            "description": "<p>The id of the User was not found.</p>"
          }
        ]
      },
      "examples": [
        {
          "title": "Error-Response:",
          "content": "HTTP/1.1 200\n{\n  \"code\": \"1\",\n   \"msg\": '响应的报错信息'\n}\n\n HTTP/1.1 200\n{\n  \"code\": \"2\",\n   \"msg\": '无数据'\n}",
          "type": "json"
        }
      ]
    },
    "version": "0.0.0",
    "filename": "app/Http/Controllers/User/PersonalCenter.php",
    "groupTitle": "User"
  },
  {
    "type": "get",
    "url": "/getProcessOrderr",
    "title": "查询用户已经处理的订单列表",
    "name": "getBuyOrder",
    "group": "User",
    "parameter": {
      "fields": {
        "Parameter": [
          {
            "group": "Parameter",
            "type": "Number",
            "optional": false,
            "field": "page",
            "description": "<p>页码</p>"
          }
        ]
      }
    },
    "success": {
      "fields": {
        "Success 200": [
          {
            "group": "Success 200",
            "type": "Number",
            "optional": false,
            "field": "user_id",
            "description": "<p>对应用户id</p>"
          },
          {
            "group": "Success 200",
            "type": "String",
            "optional": false,
            "field": "content",
            "description": "<p>购买内容.</p>"
          },
          {
            "group": "Success 200",
            "type": "String",
            "optional": false,
            "field": "name",
            "description": "<p>用户名称.</p>"
          },
          {
            "group": "Success 200",
            "type": "Number",
            "optional": false,
            "field": "qq_account",
            "description": "<p>用户qq号</p>"
          },
          {
            "group": "Success 200",
            "type": "Number",
            "optional": false,
            "field": "status",
            "description": "<p>订单状态 0未接受 1拒绝 2接受 3完成</p>"
          }
        ]
      },
      "examples": [
        {
          "title": "Success-Response:",
          "content": "HTTP/1.1 200 OK\n{\n  \"code\": \"0\",\n  \"msg\": \"success\",\n  \"data\":{\n             user_id:,\n             content:,\n             name:,\n             qq_account,\n             status:\n         }\n}",
          "type": "json"
        }
      ]
    },
    "error": {
      "fields": {
        "Error 4xx": [
          {
            "group": "Error 4xx",
            "optional": false,
            "field": "UserNotFound",
            "description": "<p>The id of the User was not found.</p>"
          }
        ]
      },
      "examples": [
        {
          "title": "Error-Response:",
          "content": "HTTP/1.1 200\n{\n  \"code\": \"1\",\n   \"msg\": '响应的报错信息'\n}\n\n HTTP/1.1 200\n{\n  \"code\": \"2\",\n   \"msg\": '无数据'\n}",
          "type": "json"
        }
      ]
    },
    "version": "0.0.0",
    "filename": "app/Http/Controllers/User/PersonalCenter.php",
    "groupTitle": "User"
  },
  {
    "type": "get",
    "url": "/getOrderList",
    "title": "用户订单列表",
    "name": "getOrderList",
    "group": "User",
    "parameter": {
      "fields": {
        "Parameter": [
          {
            "group": "Parameter",
            "type": "Number",
            "optional": false,
            "field": "page",
            "description": "<p>页码.</p>"
          }
        ]
      }
    },
    "success": {
      "fields": {
        "Success 200": [
          {
            "group": "Success 200",
            "type": "String",
            "optional": false,
            "field": "content",
            "description": "<p>订单内容</p>"
          },
          {
            "group": "Success 200",
            "type": "Number",
            "optional": false,
            "field": "created_time",
            "description": "<p>创建时间.</p>"
          },
          {
            "group": "Success 200",
            "type": "Number",
            "optional": false,
            "field": "status",
            "description": "<p>订单状态.</p>"
          },
          {
            "group": "Success 200",
            "type": "String",
            "optional": false,
            "field": "resaon",
            "description": "<p>订单拒绝的理由.</p>"
          }
        ]
      },
      "examples": [
        {
          "title": "Success-Response:",
          "content": "HTTP/1.1 200 OK\n{\n  \"code\": \"0\",\n  \"msg\": \"success\",\n  \"data\":{\n             content:'test',\n             created_time:0,\n             status:1,\n             resaon:''\n         }\n}",
          "type": "json"
        }
      ]
    },
    "error": {
      "fields": {
        "Error 4xx": [
          {
            "group": "Error 4xx",
            "optional": false,
            "field": "UserNotFound",
            "description": "<p>The id of the User was not found.</p>"
          }
        ]
      },
      "examples": [
        {
          "title": "Error-Response:",
          "content": "HTTP/1.1 200\n{\n  \"code\": \"1\",\n   \"msg\": '响应的报错信息'\n}\n\n HTTP/1.1 200\n{\n  \"code\": \"2\",\n   \"msg\": '数据加载完毕，已经无法加载相应数据'\n}",
          "type": "json"
        }
      ]
    },
    "version": "0.0.0",
    "filename": "app/Http/Controllers/User/PersonalCenter.php",
    "groupTitle": "User"
  },
  {
    "type": "get",
    "url": "/getRule",
    "title": "查看点赞币规则",
    "name": "getRule",
    "group": "User",
    "success": {
      "fields": {
        "Success 200": [
          {
            "group": "Success 200",
            "type": "String",
            "optional": false,
            "field": "content",
            "description": "<p>点赞币规则.</p>"
          }
        ]
      },
      "examples": [
        {
          "title": "Success-Response:",
          "content": "HTTP/1.1 200 OK\n{\n  \"code\": \"0\",\n  \"msg\": \"success\",\n  \"data\":{\n             content:\n         }\n}",
          "type": "json"
        }
      ]
    },
    "error": {
      "fields": {
        "Error 4xx": [
          {
            "group": "Error 4xx",
            "optional": false,
            "field": "UserNotFound",
            "description": "<p>The id of the User was not found.</p>"
          }
        ]
      },
      "examples": [
        {
          "title": "Error-Response:",
          "content": "HTTP/1.1 200\n{\n  \"code\": \"1\",\n   \"msg\": '响应的报错信息'\n}\n\n HTTP/1.1 200\n{\n  \"code\": \"2\",\n   \"msg\": '无数据'\n}",
          "type": "json"
        }
      ]
    },
    "version": "0.0.0",
    "filename": "app/Http/Controllers/User/PersonalCenter.php",
    "groupTitle": "User"
  },
  {
    "type": "get",
    "url": "/getTalk",
    "title": "获取匿名聊天",
    "name": "getTalk",
    "group": "User",
    "parameter": {
      "fields": {
        "Parameter": [
          {
            "group": "Parameter",
            "type": "Number",
            "optional": false,
            "field": "page",
            "description": "<p>页码</p>"
          }
        ]
      }
    },
    "success": {
      "fields": {
        "Success 200": [
          {
            "group": "Success 200",
            "type": "String",
            "optional": false,
            "field": "content",
            "description": "<p>匿名内容</p>"
          },
          {
            "group": "Success 200",
            "type": "int",
            "optional": false,
            "field": "create_time",
            "description": "<p>上传时间</p>"
          }
        ]
      },
      "examples": [
        {
          "title": "Success-Response:",
          "content": "HTTP/1.1 200 OK\n{\n  \"code\": \"0\",\n  \"msg\": \"success\",\n  \"data\":{\n             content:,\n             create_time:\n         }\n}",
          "type": "json"
        }
      ]
    },
    "error": {
      "fields": {
        "Error 4xx": [
          {
            "group": "Error 4xx",
            "optional": false,
            "field": "UserNotFound",
            "description": "<p>The id of the User was not found.</p>"
          }
        ]
      },
      "examples": [
        {
          "title": "Error-Response:",
          "content": "HTTP/1.1 200\n{\n  \"code\": \"1\",\n   \"msg\": '响应的报错信息'\n}\n\n HTTP/1.1 200\n{\n  \"code\": \"2\",\n   \"msg\": '无数据'\n}",
          "type": "json"
        }
      ]
    },
    "version": "0.0.0",
    "filename": "app/Http/Controllers/User/PersonalCenter.php",
    "groupTitle": "User"
  },
  {
    "type": "get",
    "url": "/getThumbupList/:id",
    "title": "显示用户的点赞记录",
    "name": "getThumbupList",
    "group": "User",
    "parameter": {
      "fields": {
        "Parameter": [
          {
            "group": "Parameter",
            "type": "Number",
            "optional": false,
            "field": "id",
            "description": "<p>用户ID</p>"
          }
        ]
      }
    },
    "success": {
      "examples": [
        {
          "title": "返回个人点赞记录",
          "content": "HTTP/1.1 200 OK\n{\n\"code\": 200,\n\"msg\": \"success\",\n\"result\": {\n\n          },\n}",
          "type": "json"
        }
      ]
    },
    "version": "0.0.0",
    "filename": "app/Http/Controllers/User/ThumbupController.php",
    "groupTitle": "User"
  },
  {
    "type": "post",
    "url": "/updateOrder",
    "title": "处理订单",
    "name": "updateOrder",
    "group": "User",
    "parameter": {
      "fields": {
        "Parameter": [
          {
            "group": "Parameter",
            "type": "Number",
            "optional": false,
            "field": "orderId",
            "description": "<p>账单Id</p>"
          }
        ]
      }
    },
    "success": {
      "examples": [
        {
          "title": "Success-Response:",
          "content": "HTTP/1.1 200 OK\n{\n  \"code\": \"0\",\n  \"msg\": \"success\"\n}",
          "type": "json"
        }
      ]
    },
    "error": {
      "fields": {
        "Error 4xx": [
          {
            "group": "Error 4xx",
            "optional": false,
            "field": "UserNotFound",
            "description": "<p>The id of the User was not found.</p>"
          }
        ]
      },
      "examples": [
        {
          "title": "Error-Response:",
          "content": "HTTP/1.1 200\n{\n  \"code\": \"1\",\n   \"msg\": '响应的报错信息'\n}",
          "type": "json"
        }
      ]
    },
    "version": "0.0.0",
    "filename": "app/Http/Controllers/User/PersonalCenter.php",
    "groupTitle": "User"
  },
  {
    "type": "post",
    "url": "/updatePassword",
    "title": "修改密码",
    "name": "updatePassword",
    "group": "User",
    "parameter": {
      "fields": {
        "Parameter": [
          {
            "group": "Parameter",
            "type": "String",
            "optional": false,
            "field": "oldPassword",
            "description": "<p>旧密码</p>"
          },
          {
            "group": "Parameter",
            "type": "String",
            "optional": false,
            "field": "newPassword",
            "description": "<p>新密码</p>"
          }
        ]
      }
    },
    "success": {
      "fields": {
        "Success 200": [
          {
            "group": "Success 200",
            "type": "Number",
            "optional": false,
            "field": "code",
            "description": "<p>状态码 0正常</p>"
          },
          {
            "group": "Success 200",
            "type": "String",
            "optional": false,
            "field": "msg",
            "description": "<p>响应信息.</p>"
          }
        ]
      },
      "examples": [
        {
          "title": "Success-Response:",
          "content": "HTTP/1.1 200 OK\n{\n  \"code\": \"0\",\n  \"msg\": \"success\",\n}",
          "type": "json"
        }
      ]
    },
    "error": {
      "fields": {
        "Error 4xx": [
          {
            "group": "Error 4xx",
            "optional": false,
            "field": "UserNotFound",
            "description": "<p>The id of the User was not found.</p>"
          }
        ]
      },
      "examples": [
        {
          "title": "Error-Response:",
          "content": "HTTP/1.1 200\n{\n  \"code\": \"1\",\n   \"msg\": '响应的报错信息'\n}",
          "type": "json"
        }
      ]
    },
    "version": "0.0.0",
    "filename": "app/Http/Controllers/User/PersonalCenter.php",
    "groupTitle": "User"
  }
]
